[{"x":-6,"y":4,"z":11,"name":"minecraft:stone"},{"x":-6,"y":5,"z":3,"name":"minecraft:stone_bricks"},{"x":-6,"y":5,"z":4,"name":"minecraft:stone_bricks"},{"x":-6,"y":5,"z":5,"name":"minecraft:stone_bricks"},{"x":-6,"y":5,"z":6,"name":"minecraft:stone"},{"x":-6,"y":5,"z":7,"name":"minecraft:stone_bricks"},{"x":-6,"y":5,"z":8,"name":"minecraft:stone"},{"x":-6,"y":5,"z":9,"name":"minecraft:stone_bricks"},{"x":-6,"y":5,"z":10,"name":"minecraft:stone_bricks"},{"x":-6,"y":5,"z":11,"name":"minecraft:stone"},{"x":-6,"y":6,"z":4,"name":"minecraft:stone"},{"x":-6,"y":6,"z":5,"name":"minecraft:stone"},{"x":-6,"y":6,"z":6,"name":"minecraft:stone"},{"x":-6,"y":6,"z":7,"name":"minecraft:stone"},{"x":-6,"y":6,"z":8,"name":"minecraft:stone"},{"x":-6,"y":6,"z":9,"name":"minecraft:stone"},{"x":-6,"y":6,"z":10,"name":"minecraft:smooth_stone"},{"x":-6,"y":6,"z":11,"name":"minecraft:stone"},{"x":-6,"y":7,"z":4,"name":"minecraft:smooth_stone"},{"x":-6,"y":7,"z":5,"name":"minecraft:stone_bricks"},{"x":-6,"y":7,"z":6,"name":"minecraft:stone"},{"x":-6,"y":7,"z":7,"name":"minecraft:smooth_stone"},{"x":-6,"y":7,"z":8,"name":"minecraft:stone"},{"x":-6,"y":7,"z":9,"name":"minecraft:stone"},{"x":-6,"y":7,"z":10,"name":"minecraft:stone_bricks"},{"x":-6,"y":7,"z":11,"name":"minecraft:stone"},{"x":-6,"y":8,"z":4,"name":"minecraft:stone_bricks"},{"x":-6,"y":8,"z":5,"name":"minecraft:smooth_stone"},{"x":-6,"y":8,"z":6,"name":"minecraft:stone"},{"x":-6,"y":8,"z":7,"name":"minecraft:stone_bricks"},{"x":-6,"y":8,"z":8,"name":"minecraft:stone_bricks"},{"x":-6,"y":8,"z":9,"name":"minecraft:stone"},{"x":-6,"y":8,"z":10,"name":"minecraft:stone"},{"x":-6,"y":8,"z":11,"name":"minecraft:stone_bricks"},{"x":-6,"y":9,"z":4,"name":"minecraft:stone"},{"x":-6,"y":9,"z":5,"name":"minecraft:stone"},{"x":-6,"y":9,"z":6,"name":"minecraft:stone"},{"x":-6,"y":9,"z":7,"name":"minecraft:stone"},{"x":-6,"y":9,"z":8,"name":"minecraft:stone"},{"x":-6,"y":9,"z":9,"name":"minecraft:smooth_stone"},{"x":-6,"y":9,"z":10,"name":"minecraft:stone_bricks"},{"x":-6,"y":9,"z":11,"name":"minecraft:stone_bricks"},{"x":-5,"y":4,"z":3,"name":"minecraft:oak_log"},{"x":-5,"y":4,"z":4,"name":"minecraft:stripped_spruce_log"},{"x":-5,"y":4,"z":5,"name":"minecraft:stripped_spruce_log"},{"x":-5,"y":4,"z":6,"name":"minecraft:stripped_spruce_log"},{"x":-5,"y":4,"z":7,"name":"minecraft:stripped_spruce_log"},{"x":-5,"y":4,"z":8,"name":"minecraft:stripped_spruce_log"},{"x":-5,"y":4,"z":9,"name":"minecraft:stripped_spruce_log"},{"x":-5,"y":4,"z":10,"name":"minecraft:stripped_spruce_log"},{"x":-5,"y":4,"z":11,"name":"minecraft:oak_log"},{"x":-5,"y":5,"z":3,"name":"minecraft:oak_log"},{"x":-5,"y":5,"z":5,"name":"minecraft:oak_log"},{"x":-5,"y":5,"z":6,"name":"minecraft:red_bed"},{"x":-5,"y":5,"z":7,"name":"minecraft:red_bed"},{"x":-5,"y":5,"z":8,"name":"minecraft:red_bed"},{"x":-5,"y":5,"z":9,"name":"minecraft:oak_log"},{"x":-5,"y":5,"z":11,"name":"minecraft:oak_log"},{"x":-5,"y":6,"z":3,"name":"minecraft:oak_log"},{"x":-5,"y":6,"z":5,"name":"minecraft:oak_log"},{"x":-5,"y":6,"z":9,"name":"minecraft:oak_log"},{"x":-5,"y":6,"z":11,"name":"minecraft:oak_log"},{"x":-5,"y":7,"z":3,"name":"minecraft:oak_log"},{"x":-5,"y":7,"z":4,"name":"minecraft:spruce_stairs"},{"x":-5,"y":7,"z":5,"name":"minecraft:oak_log"},{"x":-5,"y":7,"z":9,"name":"minecraft:oak_log"},{"x":-5,"y":7,"z":10,"name":"minecraft:spruce_stairs"},{"x":-5,"y":7,"z":11,"name":"minecraft:oak_log"},{"x":-5,"y":8,"z":3,"name":"minecraft:oak_log"},{"x":-5,"y":8,"z":4,"name":"minecraft:spruce_slab"},{"x":-5,"y":8,"z":5,"name":"minecraft:spruce_slab"},{"x":-5,"y":8,"z":6,"name":"minecraft:spruce_slab"},{"x":-5,"y":8,"z":7,"name":"minecraft:spruce_slab"},{"x":-5,"y":8,"z":8,"name":"minecraft:spruce_slab"},{"x":-5,"y":8,"z":9,"name":"minecraft:spruce_slab"},{"x":-5,"y":8,"z":10,"name":"minecraft:spruce_slab"},{"x":-5,"y":8,"z":11,"name":"minecraft:oak_log"},{"x":-5,"y":9,"z":3,"name":"minecraft:oak_log"},{"x":-5,"y":9,"z":6,"name":"minecraft:spruce_slab"},{"x":-5,"y":9,"z":7,"name":"minecraft:redstone_lamp"},{"x":-5,"y":9,"z":8,"name":"minecraft:spruce_slab"},{"x":-5,"y":9,"z":11,"name":"minecraft:oak_log"},{"x":-4,"y":4,"z":3,"name":"minecraft:stripped_spruce_log"},{"x":-4,"y":4,"z":4,"name":"minecraft:spruce_planks"},{"x":-4,"y":4,"z":5,"name":"minecraft:spruce_planks"},{"x":-4,"y":4,"z":6,"name":"minecraft:spruce_planks"},{"x":-4,"y":4,"z":7,"name":"minecraft:spruce_planks"},{"x":-4,"y":4,"z":8,"name":"minecraft:spruce_planks"},{"x":-4,"y":4,"z":9,"name":"minecraft:spruce_planks"},{"x":-4,"y":4,"z":10,"name":"minecraft:spruce_planks"},{"x":-4,"y":4,"z":11,"name":"minecraft:stripped_spruce_log"},{"x":-4,"y":5,"z":2,"name":"minecraft:stone"},{"x":-4,"y":5,"z":6,"name":"minecraft:red_bed"},{"x":-4,"y":5,"z":7,"name":"minecraft:red_bed"},{"x":-4,"y":5,"z":8,"name":"minecraft:red_bed"},{"x":-4,"y":6,"z":2,"name":"minecraft:stone"},{"x":-4,"y":7,"z":2,"name":"minecraft:stone"},{"x":-4,"y":7,"z":3,"name":"minecraft:spruce_stairs"},{"x":-4,"y":8,"z":2,"name":"minecraft:stone"},{"x":-4,"y":8,"z":3,"name":"minecraft:spruce_slab"},{"x":-4,"y":9,"z":2,"name":"minecraft:stone"},{"x":-3,"y":4,"z":3,"name":"minecraft:stripped_spruce_log"},{"x":-3,"y":4,"z":4,"name":"minecraft:spruce_planks"},{"x":-3,"y":4,"z":5,"name":"minecraft:spruce_planks"},{"x":-3,"y":4,"z":6,"name":"minecraft:spruce_planks"},{"x":-3,"y":4,"z":7,"name":"minecraft:spruce_planks"},{"x":-3,"y":4,"z":8,"name":"minecraft:spruce_planks"},{"x":-3,"y":4,"z":9,"name":"minecraft:spruce_planks"},{"x":-3,"y":4,"z":10,"name":"minecraft:spruce_planks"},{"x":-3,"y":4,"z":11,"name":"minecraft:stripped_spruce_log"},{"x":-3,"y":5,"z":2,"name":"minecraft:stone_bricks"},{"x":-3,"y":5,"z":3,"name":"minecraft:oak_log"},{"x":-3,"y":6,"z":2,"name":"minecraft:stone_bricks"},{"x":-3,"y":6,"z":3,"name":"minecraft:oak_log"},{"x":-3,"y":7,"z":2,"name":"minecraft:smooth_stone"},{"x":-3,"y":7,"z":3,"name":"minecraft:oak_log"},{"x":-3,"y":8,"z":2,"name":"minecraft:stone"},{"x":-3,"y":8,"z":3,"name":"minecraft:spruce_slab"},{"x":-3,"y":9,"z":2,"name":"minecraft:smooth_stone"},{"x":-2,"y":4,"z":3,"name":"minecraft:stripped_spruce_log"},{"x":-2,"y":4,"z":4,"name":"minecraft:spruce_planks"},{"x":-2,"y":4,"z":5,"name":"minecraft:spruce_planks"},{"x":-2,"y":4,"z":6,"name":"minecraft:spruce_planks"},{"x":-2,"y":4,"z":7,"name":"minecraft:spruce_planks"},{"x":-2,"y":4,"z":8,"name":"minecraft:spruce_planks"},{"x":-2,"y":4,"z":9,"name":"minecraft:spruce_planks"},{"x":-2,"y":4,"z":10,"name":"minecraft:spruce_planks"},{"x":-2,"y":4,"z":11,"name":"minecraft:stripped_spruce_log"},{"x":-2,"y":5,"z":2,"name":"minecraft:stone_bricks"},{"x":-2,"y":5,"z":3,"name":"minecraft:spruce_slab"},{"x":-2,"y":5,"z":4,"name":"minecraft:spruce_slab"},{"x":-2,"y":6,"z":2,"name":"minecraft:stone"},{"x":-2,"y":6,"z":3,"name":"minecraft:iron_trapdoor"},{"x":-2,"y":7,"z":2,"name":"minecraft:stone"},{"x":-2,"y":8,"z":2,"name":"minecraft:stone_bricks"},{"x":-2,"y":8,"z":3,"name":"minecraft:spruce_slab"},{"x":-2,"y":9,"z":2,"name":"minecraft:stone"},{"x":-2,"y":9,"z":3,"name":"minecraft:spruce_slab"},{"x":-1,"y":4,"z":3,"name":"minecraft:stripped_spruce_log"},{"x":-1,"y":4,"z":4,"name":"minecraft:spruce_planks"},{"x":-1,"y":4,"z":5,"name":"minecraft:spruce_planks"},{"x":-1,"y":4,"z":6,"name":"minecraft:spruce_planks"},{"x":-1,"y":4,"z":7,"name":"minecraft:spruce_planks"},{"x":-1,"y":4,"z":8,"name":"minecraft:spruce_planks"},{"x":-1,"y":4,"z":9,"name":"minecraft:spruce_planks"},{"x":-1,"y":4,"z":10,"name":"minecraft:spruce_planks"},{"x":-1,"y":4,"z":11,"name":"minecraft:stripped_spruce_log"},{"x":-1,"y":5,"z":2,"name":"minecraft:stone_bricks"},{"x":-1,"y":5,"z":3,"name":"minecraft:spruce_slab"},{"x":-1,"y":5,"z":4,"name":"minecraft:spruce_slab"},{"x":-1,"y":5,"z":5,"name":"minecraft:spruce_stairs"},{"x":-1,"y":6,"z":2,"name":"minecraft:lever"},{"x":-1,"y":6,"z":3,"name":"minecraft:black_concrete"},{"x":-1,"y":7,"z":2,"name":"minecraft:cobblestone"},{"x":-1,"y":8,"z":2,"name":"minecraft:stone"},{"x":-1,"y":8,"z":3,"name":"minecraft:spruce_slab"},{"x":-1,"y":9,"z":2,"name":"minecraft:stone"},{"x":-1,"y":9,"z":3,"name":"minecraft:redstone_lamp"},{"x":0,"y":4,"z":3,"name":"minecraft:stripped_spruce_log"},{"x":0,"y":4,"z":4,"name":"minecraft:spruce_planks"},{"x":0,"y":4,"z":5,"name":"minecraft:spruce_planks"},{"x":0,"y":4,"z":6,"name":"minecraft:spruce_planks"},{"x":0,"y":4,"z":7,"name":"minecraft:spruce_planks"},{"x":0,"y":4,"z":8,"name":"minecraft:spruce_planks"},{"x":0,"y":4,"z":9,"name":"minecraft:spruce_planks"},{"x":0,"y":4,"z":10,"name":"minecraft:spruce_planks"},{"x":0,"y":4,"z":11,"name":"minecraft:stripped_spruce_log"},{"x":0,"y":5,"z":2,"name":"minecraft:stone"},{"x":0,"y":5,"z":3,"name":"minecraft:spruce_slab"},{"x":0,"y":5,"z":4,"name":"minecraft:spruce_slab"},{"x":0,"y":6,"z":2,"name":"minecraft:stone_bricks"},{"x":0,"y":6,"z":3,"name":"minecraft:iron_trapdoor"},{"x":0,"y":7,"z":2,"name":"minecraft:cobblestone"},{"x":0,"y":8,"z":2,"name":"minecraft:smooth_stone"},{"x":0,"y":8,"z":3,"name":"minecraft:spruce_slab"},{"x":0,"y":9,"z":2,"name":"minecraft:stone_bricks"},{"x":0,"y":9,"z":3,"name":"minecraft:spruce_slab"},{"x":1,"y":4,"z":2,"name":"minecraft:stone"},{"x":1,"y":4,"z":3,"name":"minecraft:stripped_spruce_log"},{"x":1,"y":4,"z":4,"name":"minecraft:spruce_planks"},{"x":1,"y":4,"z":5,"name":"minecraft:spruce_planks"},{"x":1,"y":4,"z":6,"name":"minecraft:spruce_planks"},{"x":1,"y":4,"z":7,"name":"minecraft:spruce_planks"},{"x":1,"y":4,"z":8,"name":"minecraft:spruce_planks"},{"x":1,"y":4,"z":9,"name":"minecraft:spruce_planks"},{"x":1,"y":4,"z":10,"name":"minecraft:spruce_planks"},{"x":1,"y":4,"z":11,"name":"minecraft:stripped_spruce_log"},{"x":1,"y":5,"z":2,"name":"minecraft:stone_bricks"},{"x":1,"y":5,"z":3,"name":"minecraft:spruce_slab"},{"x":1,"y":6,"z":2,"name":"minecraft:stone_bricks"},{"x":1,"y":7,"z":2,"name":"minecraft:smooth_stone"},{"x":1,"y":8,"z":2,"name":"minecraft:stone"},{"x":1,"y":8,"z":3,"name":"minecraft:spruce_slab"},{"x":1,"y":9,"z":2,"name":"minecraft:stone_bricks"},{"x":2,"y":4,"z":2,"name":"minecraft:stone"},{"x":2,"y":4,"z":3,"name":"minecraft:stripped_spruce_log"},{"x":2,"y":4,"z":4,"name":"minecraft:spruce_planks"},{"x":2,"y":4,"z":5,"name":"minecraft:spruce_planks"},{"x":2,"y":4,"z":6,"name":"minecraft:spruce_planks"},{"x":2,"y":4,"z":7,"name":"minecraft:spruce_planks"},{"x":2,"y":4,"z":8,"name":"minecraft:spruce_planks"},{"x":2,"y":4,"z":9,"name":"minecraft:spruce_planks"},{"x":2,"y":4,"z":10,"name":"minecraft:spruce_planks"},{"x":2,"y":4,"z":11,"name":"minecraft:stripped_spruce_log"},{"x":2,"y":5,"z":2,"name":"minecraft:stone"},{"x":2,"y":5,"z":3,"name":"minecraft:spruce_slab"},{"x":2,"y":6,"z":2,"name":"minecraft:stone"},{"x":2,"y":7,"z":2,"name":"minecraft:stone"},{"x":2,"y":7,"z":3,"name":"minecraft:spruce_stairs"},{"x":2,"y":8,"z":2,"name":"minecraft:smooth_stone"},{"x":2,"y":8,"z":3,"name":"minecraft:spruce_slab"},{"x":2,"y":9,"z":2,"name":"minecraft:stone"},{"x":3,"y":4,"z":3,"name":"minecraft:stripped_spruce_log"},{"x":3,"y":4,"z":4,"name":"minecraft:stripped_spruce_log"},{"x":3,"y":4,"z":5,"name":"minecraft:stripped_spruce_log"},{"x":3,"y":4,"z":6,"name":"minecraft:stripped_spruce_log"},{"x":3,"y":4,"z":7,"name":"minecraft:stripped_spruce_log"},{"x":3,"y":4,"z":8,"name":"minecraft:stripped_spruce_log"},{"x":3,"y":4,"z":9,"name":"minecraft:stripped_spruce_log"},{"x":3,"y":4,"z":10,"name":"minecraft:stripped_spruce_log"},{"x":3,"y":4,"z":11,"name":"minecraft:stripped_spruce_log"},{"x":3,"y":5,"z":2,"name":"minecraft:stone"},{"x":3,"y":5,"z":3,"name":"minecraft:oak_log"},{"x":3,"y":6,"z":2,"name":"minecraft:stone"},{"x":3,"y":6,"z":3,"name":"minecraft:oak_log"},{"x":3,"y":7,"z":2,"name":"minecraft:stone_bricks"},{"x":3,"y":7,"z":3,"name":"minecraft:oak_log"},{"x":3,"y":8,"z":2,"name":"minecraft:stone_bricks"},{"x":3,"y":8,"z":3,"name":"minecraft:oak_log"},{"x":3,"y":9,"z":2,"name":"minecraft:stone"},{"x":3,"y":9,"z":3,"name":"minecraft:oak_log"},{"x":4,"y":4,"z":3,"name":"minecraft:stripped_spruce_log"},{"x":4,"y":4,"z":4,"name":"minecraft:spruce_planks"},{"x":4,"y":4,"z":5,"name":"minecraft:spruce_planks"},{"x":4,"y":4,"z":6,"name":"minecraft:spruce_planks"},{"x":4,"y":4,"z":7,"name":"minecraft:spruce_planks"},{"x":4,"y":4,"z":8,"name":"minecraft:spruce_planks"},{"x":4,"y":4,"z":9,"name":"minecraft:spruce_planks"},{"x":4,"y":4,"z":10,"name":"minecraft:spruce_planks"},{"x":4,"y":5,"z":2,"name":"minecraft:stone_bricks"},{"x":4,"y":6,"z":2,"name":"minecraft:smooth_stone"},{"x":4,"y":7,"z":2,"name":"minecraft:stone_bricks"},{"x":4,"y":8,"z":2,"name":"minecraft:stone"},{"x":4,"y":9,"z":2,"name":"minecraft:stone_bricks"},{"x":5,"y":4,"z":3,"name":"minecraft:stripped_spruce_log"},{"x":5,"y":4,"z":4,"name":"minecraft:spruce_planks"},{"x":5,"y":4,"z":5,"name":"minecraft:spruce_planks"},{"x":5,"y":4,"z":6,"name":"minecraft:spruce_planks"},{"x":5,"y":4,"z":7,"name":"minecraft:spruce_planks"},{"x":5,"y":4,"z":8,"name":"minecraft:spruce_planks"},{"x":5,"y":4,"z":9,"name":"minecraft:spruce_planks"},{"x":5,"y":4,"z":10,"name":"minecraft:spruce_planks"},{"x":5,"y":5,"z":2,"name":"minecraft:stone_bricks"},{"x":5,"y":6,"z":2,"name":"minecraft:stone"},{"x":5,"y":7,"z":2,"name":"minecraft:stone_bricks"},{"x":5,"y":8,"z":2,"name":"minecraft:stone"},{"x":5,"y":9,"z":2,"name":"minecraft:smooth_stone"},{"x":6,"y":4,"z":3,"name":"minecraft:stripped_spruce_log"},{"x":6,"y":4,"z":4,"name":"minecraft:spruce_planks"},{"x":6,"y":4,"z":5,"name":"minecraft:spruce_planks"},{"x":6,"y":4,"z":6,"name":"minecraft:spruce_planks"},{"x":6,"y":4,"z":7,"name":"minecraft:spruce_planks"},{"x":6,"y":4,"z":8,"name":"minecraft:spruce_planks"},{"x":6,"y":4,"z":9,"name":"minecraft:spruce_planks"},{"x":6,"y":4,"z":10,"name":"minecraft:spruce_planks"},{"x":6,"y":5,"z":2,"name":"minecraft:smooth_stone"},{"x":6,"y":6,"z":2,"name":"minecraft:stone_bricks"},{"x":6,"y":7,"z":2,"name":"minecraft:stone"},{"x":6,"y":7,"z":3,"name":"minecraft:spruce_stairs"},{"x":6,"y":8,"z":2,"name":"minecraft:stone"},{"x":6,"y":8,"z":3,"name":"minecraft:spruce_slab"},{"x":6,"y":9,"z":2,"name":"minecraft:stone_bricks"},{"x":7,"y":4,"z":3,"name":"minecraft:oak_log"},{"x":7,"y":4,"z":4,"name":"minecraft:stripped_spruce_log"},{"x":7,"y":4,"z":5,"name":"minecraft:stripped_spruce_log"},{"x":7,"y":4,"z":6,"name":"minecraft:stripped_spruce_log"},{"x":7,"y":4,"z":7,"name":"minecraft:stripped_spruce_log"},{"x":7,"y":4,"z":8,"name":"minecraft:stripped_spruce_log"},{"x":7,"y":4,"z":9,"name":"minecraft:stripped_spruce_log"},{"x":7,"y":4,"z":10,"name":"minecraft:stripped_spruce_log"},{"x":7,"y":4,"z":11,"name":"minecraft:oak_log"},{"x":7,"y":5,"z":2,"name":"minecraft:stone"},{"x":7,"y":5,"z":3,"name":"minecraft:oak_log"},{"x":7,"y":5,"z":5,"name":"minecraft:oak_log"},{"x":7,"y":5,"z":9,"name":"minecraft:oak_log"},{"x":7,"y":5,"z":11,"name":"minecraft:oak_log"},{"x":7,"y":6,"z":2,"name":"minecraft:stone_bricks"},{"x":7,"y":6,"z":3,"name":"minecraft:oak_log"},{"x":7,"y":6,"z":5,"name":"minecraft:oak_log"},{"x":7,"y":6,"z":9,"name":"minecraft:oak_log"},{"x":7,"y":6,"z":11,"name":"minecraft:oak_log"},{"x":7,"y":7,"z":2,"name":"minecraft:smooth_stone"},{"x":7,"y":7,"z":3,"name":"minecraft:oak_log"},{"x":7,"y":7,"z":4,"name":"minecraft:spruce_stairs"},{"x":7,"y":7,"z":5,"name":"minecraft:oak_log"},{"x":7,"y":7,"z":9,"name":"minecraft:oak_log"},{"x":7,"y":7,"z":10,"name":"minecraft:spruce_stairs"},{"x":7,"y":7,"z":11,"name":"minecraft:oak_log"},{"x":7,"y":8,"z":2,"name":"minecraft:stone_bricks"},{"x":7,"y":8,"z":3,"name":"minecraft:oak_log"},{"x":7,"y":8,"z":4,"name":"minecraft:spruce_slab"},{"x":7,"y":8,"z":5,"name":"minecraft:spruce_slab"},{"x":7,"y":8,"z":6,"name":"minecraft:spruce_slab"},{"x":7,"y":8,"z":7,"name":"minecraft:spruce_slab"},{"x":7,"y":8,"z":8,"name":"minecraft:spruce_slab"},{"x":7,"y":8,"z":9,"name":"minecraft:spruce_planks"},{"x":7,"y":8,"z":10,"name":"minecraft:spruce_slab"},{"x":7,"y":8,"z":11,"name":"minecraft:oak_log"},{"x":7,"y":9,"z":2,"name":"minecraft:stone"},{"x":7,"y":9,"z":6,"name":"minecraft:spruce_slab"},{"x":7,"y":9,"z":7,"name":"minecraft:spruce_slab"},{"x":7,"y":9,"z":8,"name":"minecraft:spruce_slab"},{"x":8,"y":5,"z":3,"name":"minecraft:stone"},{"x":8,"y":5,"z":4,"name":"minecraft:stone_bricks"},{"x":8,"y":5,"z":5,"name":"minecraft:stone_bricks"},{"x":8,"y":5,"z":6,"name":"minecraft:smooth_stone"},{"x":8,"y":5,"z":7,"name":"minecraft:stone"},{"x":8,"y":5,"z":8,"name":"minecraft:stone_bricks"},{"x":8,"y":5,"z":9,"name":"minecraft:smooth_stone"},{"x":8,"y":5,"z":10,"name":"minecraft:stone"},{"x":8,"y":5,"z":11,"name":"minecraft:stone"},{"x":8,"y":6,"z":3,"name":"minecraft:stone"},{"x":8,"y":6,"z":4,"name":"minecraft:stone"},{"x":8,"y":6,"z":5,"name":"minecraft:stone"},{"x":8,"y":6,"z":6,"name":"minecraft:stone_bricks"},{"x":8,"y":6,"z":7,"name":"minecraft:stone"},{"x":8,"y":6,"z":8,"name":"minecraft:stone"},{"x":8,"y":6,"z":9,"name":"minecraft:stone"},{"x":8,"y":6,"z":10,"name":"minecraft:stone"},{"x":8,"y":6,"z":11,"name":"minecraft:stone"},{"x":8,"y":7,"z":3,"name":"minecraft:stone_bricks"},{"x":8,"y":7,"z":4,"name":"minecraft:stone_bricks"},{"x":8,"y":7,"z":5,"name":"minecraft:stone"},{"x":8,"y":7,"z":6,"name":"minecraft:stone"},{"x":8,"y":7,"z":7,"name":"minecraft:stone"},{"x":8,"y":7,"z":8,"name":"minecraft:stone_bricks"},{"x":8,"y":7,"z":9,"name":"minecraft:stone_bricks"},{"x":8,"y":7,"z":10,"name":"minecraft:stone_bricks"},{"x":8,"y":7,"z":11,"name":"minecraft:smooth_stone"},{"x":8,"y":8,"z":3,"name":"minecraft:smooth_stone"},{"x":8,"y":8,"z":4,"name":"minecraft:stone_bricks"},{"x":8,"y":8,"z":5,"name":"minecraft:stone"},{"x":8,"y":8,"z":6,"name":"minecraft:stone"},{"x":8,"y":8,"z":7,"name":"minecraft:stone_bricks"},{"x":8,"y":8,"z":8,"name":"minecraft:smooth_stone"},{"x":8,"y":8,"z":9,"name":"minecraft:stone"},{"x":8,"y":8,"z":10,"name":"minecraft:stone_bricks"},{"x":8,"y":8,"z":11,"name":"minecraft:stone_bricks"},{"x":8,"y":9,"z":2,"name":"minecraft:stone"},{"x":8,"y":9,"z":3,"name":"minecraft:stone"},{"x":8,"y":9,"z":4,"name":"minecraft:smooth_stone"},{"x":8,"y":9,"z":5,"name":"minecraft:stone_bricks"},{"x":8,"y":9,"z":6,"name":"minecraft:stone_bricks"},{"x":8,"y":9,"z":7,"name":"minecraft:smooth_stone"},{"x":8,"y":9,"z":8,"name":"minecraft:stone"},{"x":8,"y":9,"z":9,"name":"minecraft:stone"},{"x":8,"y":9,"z":10,"name":"minecraft:stone_bricks"},{"x":8,"y":9,"z":11,"name":"minecraft:stone"}]
